Workbook

Sheet Overview
B2: SAP Security Control Catalog
B3: Reference model: SAP Secure Operations Map (Version 2)
B5: This catalog operationalizes SAP's Secure Operations Map into 96 auditable controls. The Map organizes SAP security into five layers, from foundational infrastructure up to organizational governance, each built on the one below it -- like courses of bricks in a defensive wall. Each layer breaks down into building blocks; each building block below carries controls in the 'Control Catalog' tab, referenced by Control ID.
B7: Layer (top → foundation) | C7: Building Blocks | D7: Focus
B8: Organization | C8: • Security Governance • Risk Management • Awareness | D8: Strategic layer. Ownership, policy, risk appetite and culture that steer everything below it: who is accountable, how risk is tracked, and how the organization keeps people security-aware.
B9: Process | C9: • Regulatory Process & Compliance • Data Privacy & Protection • Audit & Fraud Management | D9: Business-process layer. Ensures SAP-supported processes meet legal, regulatory and data-protection obligations and that fraud/misuse can be detected and investigated.
B10: Application | C10: • User & Identity Management • Authentication & Single Sign-On • Roles & Authorizations • Custom Code Security | D10: SAP application layer. Controls who can log on, what they are authorized to do, and whether custom developments introduce risk.
B11: System | C11: • Security Hardening • Secure SAP Code • Security Monitoring & Forensics | D11: SAP platform layer. Secure configuration of the SAP stack itself, patching against known vulnerabilities, and monitoring for attacks.
B12: Environment | C12: • Network Security • Operating System & Database Security • Client Security | D12: Foundation layer. Non-SAP technical infrastructure underneath and around SAP: network, OS/DB and client endpoints. Weaknesses here can undermine every control layered above.
B14: How to read the Control Catalog tab
B15: Control ID | C15: Layer abbreviation - Building block abbreviation - sequence, e.g. APP-ROL-03 = Application layer, Roles & Authorizations, control 3.
B16: Control Type | C16: Preventive (stops an event), Detective (identifies it after the fact), Corrective (fixes/limits impact), or Directive (sets policy/expectation).
B17: Control Nature | C17: Manual (human-performed), Semi-Automated (system-assisted, human-reviewed), or Automated (system-enforced/system-detected).
B18: Frequency | C18: Suggested operating cadence. Adjust to your organization's risk appetite and audit cycle.
B19: Relevant SAP Tools / T-Codes | C19: Representative transactions, tools or components typically used to implement or evidence the control -- not exhaustive.
B20: Risk Addressed | C20: The security or compliance risk the control is designed to mitigate.
B21: Evidence / Audit Artifact | C21: Example artifact an auditor or control owner could request to demonstrate the control operated.
B23: Source / reference: SAP Secure Operations Map (SAP SE), as summarized in SAP's public Secure Operations Map materials and SAP Enterprise Support security value maps. Control wording, IDs, prioritization and evidence examples in this workbook were authored to operationalize that reference model and are not an official SAP publication -- validate against current SAP guidance and your own regulatory context before adoption.

Sheet Control Catalog
A1: Control ID | B1: Layer | C1: Building Block | D1: Control Objective | E1: Control Description | F1: Control Type | G1: Control Nature | H1: Frequency | I1: Relevant SAP Tools / T-Codes | J1: Risk Addressed | K1: Evidence / Audit Artifact
A2: ORG-AWA-01 | B2: Organization | C2: Awareness | D2: Build a security-conscious user base | E2: Deliver role-based security awareness training (end users, Basis administrators, developers, business process owners) covering SAP-relevant risks and responsibilities. | F2: Preventive | G2: Manual / Semi-Automated | H2: Annual; event-driven (onboarding) | I2: LMS training modules | J2: User behavior undermining technical controls (e.g., credential sharing, phishing susceptibility) | K2: Training completion records
A3: ORG-AWA-02 | B3: Organization | C3: Awareness | D3: Test and reinforce phishing/social-engineering resilience | E3: Run periodic phishing and social engineering simulation exercises relevant to SAP access scenarios, with targeted follow-up training for those who fall for simulations. | F3: Detective | G3: Semi-Automated | H3: Quarterly/Semi-Annual | I3: Phishing simulation platform | J3: Successful social engineering leading to credential compromise | K3: Simulation results and follow-up training log
A4: ORG-AWA-03 | B4: Organization | C4: Awareness | D4: Set expectations from day one for sensitive access | E4: Provide a dedicated security briefing for new users receiving privileged or sensitive SAP access as part of onboarding. | F4: Preventive | G4: Manual | H4: Event-driven | I4: Onboarding checklist | J4: New privileged users unaware of specific obligations/risks | K4: Onboarding briefing sign-off
A5: ORG-AWA-04 | B5: Organization | C5: Awareness | D5: Keep the organization current on policy and incident learnings | E5: Regularly communicate security policy updates and lessons learned from incidents/near-misses to relevant SAP user and administrator populations. | F5: Preventive | G5: Manual | H5: Quarterly; event-driven | I5: Communication channels/newsletters | J5: Repeat incidents resulting from unaddressed root causes | K5: Communication archive
A6: ORG-AWA-05 | B6: Organization | C6: Awareness | D6: Measure whether awareness efforts are effective | E6: Track training completion rates, simulation results and (where feasible) behavior metrics to assess and improve awareness program effectiveness. | F6: Detective | G6: Semi-Automated | H6: Quarterly | I6: LMS reporting, awareness dashboard | J6: Ongoing investment in an awareness program without evidence of effectiveness | K6: Awareness metrics report
A7: ORG-AWA-06 | B7: Organization | C7: Awareness | D7: Reduce vulnerabilities introduced by developers | E7: Provide specialized secure-coding training for ABAP/UI5 developers, refreshed periodically and aligned to findings from code scanning tools. | F7: Preventive | G7: Manual | H7: Annual | I7: Developer training curriculum | J7: Recurring vulnerability classes stemming from untrained developers | K7: Developer training completion record
A8: ORG-RSK-01 | B8: Organization | C8: Risk Management | D8: Maintain visibility of SAP-specific risk | E8: Maintain a risk register for SAP security risks, integrated with the organization's Enterprise Risk Management process and reviewed by risk owners. | F8: Directive | G8: Manual | H8: Quarterly | I8: ERM/GRC risk register | J8: SAP-specific risks not visible at the enterprise risk level | K8: Risk register extract
A9: ORG-RSK-02 | B9: Organization | C9: Risk Management | D9: Identify exploitable weaknesses before attackers do | E9: Perform periodic vulnerability assessments and penetration tests of the SAP landscape (external, internal and application-layer) using qualified testers. | F9: Detective | G9: Manual / Semi-Automated | H9: Annual; event-driven | I9: VA/PT tooling and methodology | J9: Unknown exploitable vulnerabilities remaining in production | K9: VA/PT report and remediation plan
A10: ORG-RSK-03 | B10: Organization | C10: Risk Management | D10: Focus remediation effort where risk is highest | E10: Apply a risk-based prioritization methodology to remediation of identified vulnerabilities and control gaps, factoring exploitability and business impact. | F10: Directive | G10: Manual | H10: Continuous (per finding) | I10: Risk scoring methodology | J10: Remediation effort misallocated to lower-impact issues | K10: Prioritized remediation backlog
A11: ORG-RSK-04 | B11: Organization | C11: Risk Management | D11: Understand criticality to inform control investment | E11: Classify SAP systems by business criticality and data sensitivity (business impact analysis) to calibrate the intensity of security controls applied. | F11: Directive | G11: Manual | H11: Annual | I11: Business Impact Analysis (BIA) methodology | J11: Under- or over-investment in controls relative to actual system criticality | K11: BIA/criticality classification document
A12: ORG-RSK-05 | B12: Organization | C12: Risk Management | D12: Manage risk introduced by SAP add-ons and integrations | E12: Assess third-party SAP add-ons, ISV solutions and integration partners for security risk prior to onboarding and periodically thereafter. | F12: Preventive | G12: Manual | H12: Event-driven; annual review | I12: Vendor/supply-chain risk assessment | J12: Vulnerabilities introduced via third-party code/integrations | K12: Vendor risk assessment record
... A97: ENV-OSD-06 | B97: Environment | C97: Operating System & Database Security | D97: Enforce tenant/schema isolation in shared database environments | E97: Configure and verify tenant database or schema separation so that one application/customer cannot access another's data in multi-tenant or shared HANA landscapes. | F97: Preventive | G97: Semi-Automated | H97: Annual; event-driven | I97: HANA Multitenant Database Containers (MDC), schema privileges | J97: Cross-tenant data leakage | K97: Tenant isolation test results, privilege review

Sheet Summary
B2: Control Count Summary
B3: Counts recalculate automatically from the Control Catalog tab.
B5: By Layer
B6: Layer | C6: Building Blocks | D6: # Controls
B7: Organization | C7: 3 | D7: =COUNTIF('Control Catalog'!$B$2:$B$97,B7) -> 18
B8: Process | C8: 3 | D8: =COUNTIF('Control Catalog'!$B$2:$B$97,B8) -> 18
B9: Application | C9: 4 | D9: =COUNTIF('Control Catalog'!$B$2:$B$97,B9) -> 24
B10: System | C10: 3 | D10: =COUNTIF('Control Catalog'!$B$2:$B$97,B10) -> 18
B11: Environment | C11: 3 | D11: =COUNTIF('Control Catalog'!$B$2:$B$97,B11) -> 18
B12: Total | D12: =SUM(D7:D11) -> 96
B14: By Building Block
B15: Building Block | C15: Layer | D15: # Controls
B16: Security Governance | C16: Organization | D16: =COUNTIF('Control Catalog'!$C$2:$C$97,B16) -> 6
B17: Risk Management | C17: Organization | D17: =COUNTIF('Control Catalog'!$C$2:$C$97,B17) -> 6
B18: Awareness | C18: Organization | D18: =COUNTIF('Control Catalog'!$C$2:$C$97,B18) -> 6
B19: Regulatory Process & Compliance | C19: Process | D19: =COUNTIF('Control Catalog'!$C$2:$C$97,B19) -> 6
B20: Data Privacy & Protection | C20: Process | D20: =COUNTIF('Control Catalog'!$C$2:$C$97,B20) -> 6
B21: Audit & Fraud Management | C21: Process | D21: =COUNTIF('Control Catalog'!$C$2:$C$97,B21) -> 6
B22: User & Identity Management | C22: Application | D22: =COUNTIF('Control Catalog'!$C$2:$C$97,B22) -> 6
B23: Authentication & Single Sign-On | C23: Application | D23: =COUNTIF('Control Catalog'!$C$2:$C$97,B23) -> 6
B24: Roles & Authorizations | C24: Application | D24: =COUNTIF('Control Catalog'!$C$2:$C$97,B24) -> 6
B25: Custom Code Security | C25: Application | D25: =COUNTIF('Control Catalog'!$C$2:$C$97,B25) -> 6
B26: Security Hardening | C26: System | D26: =COUNTIF('Control Catalog'!$C$2:$C$97,B26) -> 6
B27: Secure SAP Code | C27: System | D27: =COUNTIF('Control Catalog'!$C$2:$C$97,B27) -> 6
... B31: Client Security | C31: Environment | D31: =COUNTIF('Control Catalog'!$C$2:$C$97,B31) -> 6
